mcp_arangodb_async/__init__.py
mcp_arangodb_async/__main__.py
mcp_arangodb_async/backup.py
mcp_arangodb_async/cli_db.py
mcp_arangodb_async/cli_db_arango.py
mcp_arangodb_async/cli_health.py
mcp_arangodb_async/cli_user.py
mcp_arangodb_async/cli_utils.py
mcp_arangodb_async/config.py
mcp_arangodb_async/config_loader.py
mcp_arangodb_async/content_converter.py
mcp_arangodb_async/db.py
mcp_arangodb_async/db_resolver.py
mcp_arangodb_async/entry.py
mcp_arangodb_async/graph_backup.py
mcp_arangodb_async/handlers.py
mcp_arangodb_async/hatch_metadata.json
mcp_arangodb_async/health.py
mcp_arangodb_async/http_transport.py
mcp_arangodb_async/models.py
mcp_arangodb_async/multi_db_manager.py
mcp_arangodb_async/session_state.py
mcp_arangodb_async/session_utils.py
mcp_arangodb_async/tool_registry.py
mcp_arangodb_async/tools.py
mcp_arangodb_async/transport_config.py
mcp_arangodb_async/types.py
mcp_arangodb_async-0.5.4.dist-info/METADATA
mcp_arangodb_async-0.5.4.dist-info/WHEEL
mcp_arangodb_async-0.5.4.dist-info/entry_points.txt
mcp_arangodb_async-0.5.4.dist-info/licenses/LICENSE
mcp_arangodb_async-0.5.4.dist-info/RECORD
