Metadata-Version: 2.4
Name: mcp-arangodb-async
Version: 0.5.4
Summary: A Model Context Protocol server for ArangoDB
Project-URL: Homepage, https://github.com/PCfVW/mcp-arango-async
Project-URL: Repository, https://github.com/PCfVW/mcp-arango-async
Project-URL: Issues, https://github.com/PCfVW/mcp-arango-async/issues
Author: Eric Jacopin, eric.jacopin@protonmail.com
License-Expression: Apache-2.0
License-File: LICENSE
Keywords: aql,arangodb,async,database,graph,mcp,mcp-server,model-context-protocol
Classifier: Development Status :: 4 - Beta
Classifier: Intended Audience :: Developers
Classifier: License :: OSI Approved :: Apache Software License
Classifier: Programming Language :: Python :: 3
Classifier: Programming Language :: Python :: 3.11
Classifier: Programming Language :: Python :: 3.12
Classifier: Topic :: Database
Classifier: Topic :: Software Development :: Libraries :: Python Modules
Requires-Python: >=3.11
Requires-Dist: jsonschema<5,>=4
Requires-Dist: mcp>=1.18.0
Requires-Dist: pydantic<3,>=2
Requires-Dist: python-arango<9,>=8.2.2
Requires-Dist: python-dotenv<2,>=1.0
Requires-Dist: starlette<1.0,>=0.27.0
Requires-Dist: uvicorn[standard]<1.0,>=0.23.0
Provides-Extra: dev
Requires-Dist: black>=25.0.0; extra == 'dev'
Requires-Dist: docker>=7.0.0; extra == 'dev'
Requires-Dist: pytest-asyncio<2,>=0.24; extra == 'dev'
Requires-Dist: pytest<9,>=8; extra == 'dev'
Requires-Dist: ruff>=0.1.0; extra == 'dev'
Requires-Dist: tabulate>=0.9.0; extra == 'dev'
